<?xml version="1.0" encoding="UTF-8"?>
<accounts>
  <user id="64a97c4fa45db">
    <username>jcarlo</username>
    <password>$2y$10$VPrO2Ni1D8/daRRNukhOK.9qaihX3nspgHXGMf4q7H4N806mlSrVO</password>
    <email>jc@gmail.com</email>
  </user>
  <user id="64b69a32de567">
    <username>jcarlo2</username>
    <password>$2y$10$QqRPecAH6fz6maaKAiLwQeBOwIb.aEnF8MXTTS9FIFVvrz/cIrosC</password>
    <email>admin@test.com</email>
  </user>
  <user id="64ba9fbfafd82">
    <username>carlo</username>
    <password>$2y$10$g3/kV/SH2ReTcL3qwEmaxewTc0F4gW5XbRquAMiWgeX0Nz989VKaq</password>
    <email>johncarlolabanero@gmail.com</email>
  </user>
</accounts>
